{
  "binance|ASTER/USDT|ema_cross_intrabar": {
    "at": "intrabar",
    "last_candle": 1783645500000,
    "side": "INTRABAR BUY"
  },
  "binance|ASTER/USDT|ema_cross_rsi": {
    "at": "2026-07-10 11:35 UTC",
    "last_candle": 1783683300000,
    "side": "WEAK SELL"
  },
  "binance|ASTER/USDT|ema_cross_soon": {
    "at": "2026-07-10 12:25 UTC",
    "last_candle": 1783686300000
  },
  "binance|BNB/USDT|ema_cross_intrabar": {
    "at": "intrabar",
    "last_candle": 1783644900000,
    "side": "INTRABAR BUY"
  },
  "binance|BNB/USDT|ema_cross_rsi": {
    "at": "2026-07-10 11:20 UTC",
    "last_candle": 1783682400000,
    "side": "WEAK SELL"
  },
  "binance|BNB/USDT|ema_cross_soon": {
    "at": "2026-07-10 12:30 UTC",
    "last_candle": 1783686600000
  },
  "binance|BTC/USDT|ema_cross_intrabar": {
    "at": "intrabar",
    "last_candle": 1783561500000,
    "pending": {
      "candle": 1783618500000,
      "seen": 1,
      "side": "INTRABAR BUY"
    },
    "side": "INTRABAR SELL"
  },
  "binance|BTC/USDT|ema_cross_rsi": {
    "at": "2026-07-10 12:45 UTC",
    "last_candle": 1783687500000,
    "side": "WEAK SELL"
  },
  "binance|BTC/USDT|ema_cross_soon": {
    "at": "2026-07-10 12:35 UTC",
    "last_candle": 1783686900000
  },
  "binance|ETH/USDT|ema_cross_intrabar": {
    "at": "intrabar",
    "last_candle": 1783646400000,
    "side": "INTRABAR BUY"
  },
  "binance|ETH/USDT|ema_cross_rsi": {
    "at": "2026-07-10 12:45 UTC",
    "last_candle": 1783687500000,
    "side": "WEAK SELL"
  },
  "binance|ETH/USDT|ema_cross_soon": {
    "at": "2026-07-10 12:40 UTC",
    "last_candle": 1783687200000
  },
  "binance|SOL/USDT|ema_cross_intrabar": {
    "at": "intrabar",
    "last_candle": 1783671300000,
    "side": "INTRABAR BUY"
  },
  "binance|SOL/USDT|ema_cross_rsi": {
    "at": "2026-07-10 11:50 UTC",
    "last_candle": 1783684200000,
    "side": "WEAK SELL"
  },
  "binance|SOL/USDT|ema_cross_soon": {
    "at": "2026-07-10 12:25 UTC",
    "last_candle": 1783686300000
  },
  "kucoin|HYPE/USDT|ema_cross_intrabar": {
    "at": "intrabar",
    "last_candle": 1783668300000,
    "side": "INTRABAR BUY"
  },
  "kucoin|HYPE/USDT|ema_cross_rsi": {
    "at": "2026-07-10 11:40 UTC",
    "last_candle": 1783683600000,
    "side": "WEAK SELL"
  },
  "kucoin|HYPE/USDT|ema_cross_soon": {
    "at": "2026-07-10 11:35 UTC",
    "last_candle": 1783683300000
  }
}
