{
  "binance|ASTER/USDT|ema_cross_intrabar": {
    "at": "intrabar",
    "last_candle": 1783326900000,
    "side": "INTRABAR SELL"
  },
  "binance|ASTER/USDT|ema_cross_rsi": {
    "at": "2026-07-06 08:35 UTC",
    "last_candle": 1783326900000,
    "side": "WEAK SELL"
  },
  "binance|ASTER/USDT|ema_cross_soon": {
    "at": "2026-07-06 10:25 UTC",
    "last_candle": 1783333500000,
    "side": "NEAR-BUY"
  },
  "binance|BNB/USDT|ema_cross_intrabar": {
    "at": "intrabar",
    "last_candle": 1783299300000,
    "side": "INTRABAR BUY"
  },
  "binance|BNB/USDT|ema_cross_rsi": {
    "at": "2026-07-06 01:50 UTC",
    "last_candle": 1783302600000,
    "side": "WEAK SELL"
  },
  "binance|BNB/USDT|ema_cross_soon": {
    "at": "2026-07-06 10:25 UTC",
    "last_candle": 1783333500000,
    "side": "NEAR-BUY"
  },
  "binance|BTC/USDT|ema_cross_intrabar": {
    "at": "intrabar",
    "last_candle": 1783298700000,
    "side": "INTRABAR BUY"
  },
  "binance|BTC/USDT|ema_cross_rsi": {
    "at": "2026-07-06 10:30 UTC",
    "last_candle": 1783333800000,
    "side": "WEAK BUY"
  },
  "binance|BTC/USDT|ema_cross_soon": {
    "at": "2026-07-06 10:20 UTC",
    "last_candle": 1783333200000
  },
  "binance|ETH/USDT|ema_cross_intrabar": {
    "at": "intrabar",
    "last_candle": 1783326600000,
    "side": "INTRABAR SELL"
  },
  "binance|ETH/USDT|ema_cross_rsi": {
    "at": "2026-07-06 10:25 UTC",
    "last_candle": 1783333500000,
    "side": "WEAK BUY"
  },
  "binance|ETH/USDT|ema_cross_soon": {
    "at": "2026-07-06 10:15 UTC",
    "last_candle": 1783332900000
  },
  "binance|SOL/USDT|ema_cross_intrabar": {
    "at": "intrabar",
    "last_candle": 1783326900000,
    "side": "INTRABAR SELL"
  },
  "binance|SOL/USDT|ema_cross_rsi": {
    "at": "2026-07-06 08:35 UTC",
    "last_candle": 1783326900000,
    "side": "SELL"
  },
  "binance|SOL/USDT|ema_cross_soon": {
    "at": "2026-07-06 10:20 UTC",
    "last_candle": 1783333200000,
    "side": "NEAR-BUY"
  },
  "kucoin|HYPE/USDT|ema_cross_intrabar": {
    "at": "intrabar",
    "last_candle": 1783304700000,
    "side": "INTRABAR BUY"
  },
  "kucoin|HYPE/USDT|ema_cross_rsi": {
    "at": "2026-07-06 10:20 UTC",
    "last_candle": 1783333200000,
    "side": "WEAK BUY"
  },
  "kucoin|HYPE/USDT|ema_cross_soon": {
    "at": "2026-07-06 10:15 UTC",
    "last_candle": 1783332900000
  }
}
