{
  "binance|ASTER/USDT|ema_cross_intrabar": {
    "at": "intrabar",
    "last_candle": 1783907100000,
    "side": "INTRABAR SELL"
  },
  "binance|ASTER/USDT|ema_cross_rsi": {
    "at": "2026-07-13 01:45 UTC",
    "last_candle": 1783907100000,
    "side": "SELL"
  },
  "binance|ASTER/USDT|ema_cross_soon": {
    "at": "2026-07-14 03:30 UTC",
    "last_candle": 1783999800000
  },
  "binance|BNB/USDT|ema_cross_intrabar": {
    "at": "intrabar",
    "last_candle": 1783566000000,
    "side": "INTRABAR SELL"
  },
  "binance|BNB/USDT|ema_cross_rsi": {
    "at": "2026-07-12 18:15 UTC",
    "last_candle": 1783880100000,
    "side": "WEAK SELL"
  },
  "binance|BNB/USDT|ema_cross_soon": {
    "at": "2026-07-14 06:30 UTC",
    "last_candle": 1784010600000,
    "side": "NEAR-SELL"
  },
  "binance|BTC/USDT|ema_cross_intrabar": {
    "at": "intrabar",
    "last_candle": 1783902600000,
    "side": "INTRABAR BUY"
  },
  "binance|BTC/USDT|ema_cross_rsi": {
    "at": "2026-07-12 21:45 UTC",
    "last_candle": 1783892700000,
    "side": "SELL"
  },
  "binance|BTC/USDT|ema_cross_soon": {
    "at": "2026-07-13 01:00 UTC",
    "last_candle": 1783904400000
  },
  "binance|ETH/USDT|ema_cross_intrabar": {
    "at": "intrabar",
    "last_candle": 1783908000000,
    "side": "INTRABAR SELL"
  },
  "binance|ETH/USDT|ema_cross_rsi": {
    "at": "2026-07-13 02:00 UTC",
    "last_candle": 1783908000000,
    "side": "WEAK SELL"
  },
  "binance|ETH/USDT|ema_cross_soon": {
    "at": "2026-07-13 01:45 UTC",
    "last_candle": 1783907100000
  },
  "binance|SOL/USDT|ema_cross_intrabar": {
    "at": "intrabar",
    "last_candle": 1783998900000,
    "side": "INTRABAR SELL"
  },
  "binance|SOL/USDT|ema_cross_rsi": {
    "at": "2026-07-14 03:45 UTC",
    "last_candle": 1784000700000,
    "side": "WEAK BUY"
  },
  "binance|SOL/USDT|ema_cross_soon": {
    "at": "2026-07-14 06:45 UTC",
    "last_candle": 1784011500000,
    "side": "NEAR-SELL"
  },
  "kucoin|HYPE/USDT|ema_cross_intrabar": {
    "at": "intrabar",
    "last_candle": 1783847700000,
    "side": "INTRABAR SELL"
  },
  "kucoin|HYPE/USDT|ema_cross_rsi": {
    "at": "2026-07-14 05:00 UTC",
    "last_candle": 1784005200000,
    "side": "WEAK BUY"
  },
  "kucoin|HYPE/USDT|ema_cross_soon": {
    "at": "2026-07-14 04:30 UTC",
    "last_candle": 1784003400000
  }
}
