{
  "binance|ASTER/USDT|ema_cross_intrabar": {
    "at": "intrabar",
    "last_candle": 1783236300000,
    "side": "INTRABAR SELL"
  },
  "binance|ASTER/USDT|ema_cross_rsi": {
    "at": "2026-07-05 09:30 UTC",
    "last_candle": 1783243800000,
    "side": "WEAK SELL"
  },
  "binance|ASTER/USDT|ema_cross_soon": {
    "at": "2026-07-05 09:25 UTC",
    "last_candle": 1783243500000
  },
  "binance|BNB/USDT|ema_cross_intrabar": {
    "at": "intrabar",
    "last_candle": 1783244400000,
    "side": "INTRABAR SELL"
  },
  "binance|BNB/USDT|ema_cross_rsi": {
    "at": "2026-07-05 09:40 UTC",
    "last_candle": 1783244400000,
    "side": "WEAK SELL"
  },
  "binance|BNB/USDT|ema_cross_soon": {
    "at": "2026-07-05 10:40 UTC",
    "last_candle": 1783248000000,
    "side": "NEAR-BUY"
  },
  "binance|BTC/USDT|ema_cross_intrabar": {
    "at": "intrabar",
    "last_candle": 1783242900000,
    "side": "INTRABAR SELL"
  },
  "binance|BTC/USDT|ema_cross_rsi": {
    "at": "2026-07-05 09:15 UTC",
    "last_candle": 1783242900000,
    "side": "WEAK SELL"
  },
  "binance|BTC/USDT|ema_cross_soon": {
    "at": "2026-07-05 08:50 UTC",
    "last_candle": 1783241400000
  },
  "binance|ETH/USDT|ema_cross_intrabar": {
    "at": "intrabar",
    "last_candle": 1783200600000,
    "side": "INTRABAR BUY"
  },
  "binance|ETH/USDT|ema_cross_rsi": {
    "at": "2026-07-05 09:15 UTC",
    "last_candle": 1783242900000,
    "side": "WEAK SELL"
  },
  "binance|ETH/USDT|ema_cross_soon": {
    "at": "2026-07-05 08:55 UTC",
    "last_candle": 1783241700000
  },
  "binance|SOL/USDT|ema_cross_intrabar": {
    "at": "intrabar",
    "last_candle": 1783241400000,
    "side": "INTRABAR SELL"
  },
  "binance|SOL/USDT|ema_cross_rsi": {
    "at": "2026-07-05 08:50 UTC",
    "last_candle": 1783241400000,
    "side": "WEAK SELL"
  },
  "binance|SOL/USDT|ema_cross_soon": {
    "at": "2026-07-05 10:30 UTC",
    "last_candle": 1783247400000,
    "side": "NEAR-BUY"
  },
  "kucoin|HYPE/USDT|ema_cross_intrabar": {
    "at": "intrabar",
    "last_candle": 1783244400000,
    "side": "INTRABAR SELL"
  },
  "kucoin|HYPE/USDT|ema_cross_rsi": {
    "at": "2026-07-05 10:10 UTC",
    "last_candle": 1783246200000,
    "side": "WEAK BUY"
  },
  "kucoin|HYPE/USDT|ema_cross_soon": {
    "at": "2026-07-05 10:05 UTC",
    "last_candle": 1783245900000
  }
}
